setup.py
zen.py
Zen.egg-info/PKG-INFO
Zen.egg-info/SOURCES.txt
Zen.egg-info/dependency_links.txt
Zen.egg-info/requires.txt
Zen.egg-info/top_level.txt