Metadata-Version: 1.0
Name: Zen
Version: 0.1
Summary: A simple way to access the ZenDesk v2 API via Python.
Home-page: https://github.com/caesarnine/zen_python
Author: Binal Patel
Author-email: binalkp91@gmail.com
License: UNKNOWN
Keywords: zendesk api ticketing helpdesk
Platform: UNKNOWN
